g2g_scim_sync/__init__.py
g2g_scim_sync/cli.py
g2g_scim_sync/config.py
g2g_scim_sync/github_client.py
g2g_scim_sync/google_client.py
g2g_scim_sync/models.py
g2g_scim_sync/sync_engine.py
g2g_scim_sync-1.0.0.dist-info/METADATA
g2g_scim_sync-1.0.0.dist-info/WHEEL
g2g_scim_sync-1.0.0.dist-info/entry_points.txt
g2g_scim_sync-1.0.0.dist-info/licenses/LICENSE
g2g_scim_sync-1.0.0.dist-info/RECORD
