Metadata-Version: 2.4
Name: g2g-scim-sync
Version: 1.0.0
Summary: Google Workspace to GitHub Enterprise SCIM synchronization tool
Project-URL: Homepage, https://github.com/gmr/g2g-scim-sync
Project-URL: Documentation, https://github.com/gmr/g2g-scim-sync
Project-URL: Repository, https://github.com/gmr/g2g-scim-sync
Project-URL: Bug Tracker, https://github.com/gmr/g2g-scim-sync/issues
Author-email: "Gavin M. Roy" <gavinr@aweber.com>
License: BSD-3-Clause
License-File: LICENSE
Keywords: github-enterprise,google-workspace,identity-management,provisioning,scim
Classifier: Development Status :: 4 - Beta
Classifier: Environment :: Console
Classifier: Intended Audience :: System Administrators
Classifier: License :: OSI Approved :: BSD License
Classifier: Natural Language :: English
Classifier: Operating System :: OS Independent
Classifier: Programming Language :: Python :: 3
Classifier: Programming Language :: Python :: 3.12
Classifier: Programming Language :: Python :: 3.13
Classifier: Topic :: Software Development :: Libraries :: Python Modules
Classifier: Topic :: System :: Systems Administration :: Authentication/Directory
Classifier: Typing :: Typed
Requires-Python: >=3.12
Requires-Dist: email-validator>=2.0.0
Requires-Dist: google-api-python-client>=2.0.0
Requires-Dist: google-auth>=2.0.0
Requires-Dist: httpx>=0.27.0
Requires-Dist: pydantic<3,>=2.11.3
Provides-Extra: dev
Requires-Dist: build; extra == 'dev'
Requires-Dist: coverage[toml]; extra == 'dev'
Requires-Dist: pre-commit; extra == 'dev'
Requires-Dist: pytest; extra == 'dev'
Requires-Dist: pytest-asyncio; extra == 'dev'
Requires-Dist: pytest-cov; extra == 'dev'
Requires-Dist: ruff; extra == 'dev'
